bin/account-scout
bin/airdrop
bin/balance-account
bin/balance-wallet
bin/cancel-my-orders
bin/cancel-order
bin/close-token-account
bin/close-wrapped-sol-account
bin/crank-market
bin/delegate-account
bin/deposit
bin/download-trades
bin/ensure-account
bin/ensure-associated-token-account
bin/ensure-open-orders
bin/generate-keypair
bin/keeper
bin/log-subscribe
bin/mango-explorer-version
bin/market-buy
bin/market-sell
bin/marketmaker
bin/mint
bin/notify-below-minimum-sol-balance
bin/place-order
bin/redeem-mango
bin/redeem-pnl
bin/register-referrer-id
bin/report-transactions
bin/send-notification
bin/send-sols
bin/send-token
bin/set-discoverable-referrer
bin/settle-market
bin/show-account-balances
bin/show-account-dataframe
bin/show-account-info
bin/show-accounts
bin/show-address
bin/show-all-token-accounts
bin/show-delegated-accounts
bin/show-discoverable-referrer
bin/show-file
bin/show-funding-rates
bin/show-group
bin/show-group-prices
bin/show-interest-rates
bin/show-liquidity-mining-info
bin/show-market
bin/show-model-state
bin/show-my-orders
bin/show-open-orders
bin/show-orderbook
bin/show-price
bin/show-serum-open-orders
bin/show-token-balance
bin/show-transaction
bin/show-wrapped-sol
bin/simple-marketmaker
bin/unwrap-sol
bin/watch-address
bin/watch-minimum-balances
bin/who-am-i
bin/withdraw
bin/wrap-sol
data/entropy_logs.json
data/ids.json
data/mango_ids.json
data/nonspl.instrumentlist.devnet.json
data/nonspl.instrumentlist.json
data/overrides.tokenlist.devnet.json
data/overrides.tokenlist.json
data/solana.tokenlist.devnet.json
data/solana.tokenlist.json
entropy/.README.rst.swp
entropy/__init__.py
entropy/account.py
entropy/accountflags.py
entropy/accountinfo.py
entropy/accountinfoconverter.py
entropy/accountscout.py
entropy/addressableaccount.py
entropy/arguments.py
entropy/cache.py
entropy/client.py
entropy/combinableinstructions.py
entropy/constants.py
entropy/context.py
entropy/contextbuilder.py
entropy/datetimes.py
entropy/encoding.py
entropy_explorer-1.0.8.dist-info/LICENSE
entropy_explorer-1.0.8.dist-info/WHEEL
entropy_explorer-1.0.8.dist-info/METADATA
entropy_explorer-1.0.8.dist-info/RECORD
