Metadata-Version: 2.1
Name: entropy-explorer
Version: 1.0.8
Summary: Python integration for https://entropy.trade
Home-page: https://entropy.trade
License: MIT
Author: thiccythot
Requires-Python: >=3.6,<3.11
Classifier: License :: OSI Approved :: MIT License
Classifier: Programming Language :: Python :: 3
Classifier: Programming Language :: Python :: 3.10
Classifier: Programming Language :: Python :: 3.6
Classifier: Programming Language :: Python :: 3.7
Classifier: Programming Language :: Python :: 3.8
Classifier: Programming Language :: Python :: 3.9
Requires-Dist: Rx (>=3.2.0,<4.0.0)
Requires-Dist: jsons (>=1.6.1,<2.0.0)
Requires-Dist: numpy (>=1.22.1,<2.0.0)
Requires-Dist: pandas (>=1.4.1,<2.0.0)
Requires-Dist: pyserum (>=0.5.0a0,<0.6.0)
Requires-Dist: python-dateutil (>=2.8.2,<3.0.0)
Requires-Dist: requests (>=2.27.1,<3.0.0)
Requires-Dist: rxpy-backpressure (>=1.0.0,<2.0.0)
Requires-Dist: solana (>=0.21.0,<0.22.0)
Requires-Dist: websocket-client (>=1.2.1,<2.0.0)
Requires-Dist: zstandard (>=0.17.0,<0.18.0)
Project-URL: Repository, https://github.com/friktion-labs/entropy-explorer
